fds/__init__.py
fds/sdk/__init__.py
fds/sdk/FactSetOwnershipReportBuilder/__init__.py
fds/sdk/FactSetOwnershipReportBuilder/api_client.py
fds/sdk/FactSetOwnershipReportBuilder/configuration.py
fds/sdk/FactSetOwnershipReportBuilder/exceptions.py
fds/sdk/FactSetOwnershipReportBuilder/model_utils.py
fds/sdk/FactSetOwnershipReportBuilder/rest.py
fds/sdk/FactSetOwnershipReportBuilder/api/__init__.py
fds/sdk/FactSetOwnershipReportBuilder/api/ownership_api.py
fds/sdk/FactSetOwnershipReportBuilder/apis/__init__.py
fds/sdk/FactSetOwnershipReportBuilder/model/__init__.py
fds/sdk/FactSetOwnershipReportBuilder/model/error_object.py
fds/sdk/FactSetOwnershipReportBuilder/model/error_object_links.py
fds/sdk/FactSetOwnershipReportBuilder/model/error_object_source.py
fds/sdk/FactSetOwnershipReportBuilder/model/error_response.py
fds/sdk/FactSetOwnershipReportBuilder/model/error_with_meta_response.py
fds/sdk/FactSetOwnershipReportBuilder/model/meta.py
fds/sdk/FactSetOwnershipReportBuilder/model/response_holders.py
fds/sdk/FactSetOwnershipReportBuilder/model/response_ultimate_parent.py
fds/sdk/FactSetOwnershipReportBuilder/models/__init__.py
fds.sdk.FactSetOwnershipReportBuilder-1.1.6.dist-info/LICENSE
fds.sdk.FactSetOwnershipReportBuilder-1.1.6.dist-info/METADATA
fds.sdk.FactSetOwnershipReportBuilder-1.1.6.dist-info/WHEEL
fds.sdk.FactSetOwnershipReportBuilder-1.1.6.dist-info/top_level.txt
fds.sdk.FactSetOwnershipReportBuilder-1.1.6.dist-info/RECORD
